cardiac_geometries/__init__.py
cardiac_geometries/aha.py
cardiac_geometries/cli.py
cardiac_geometries/geometry.py
cardiac_geometries/gui.py
cardiac_geometries/mesh.py
cardiac_geometries/utils.py
cardiac_geometries/fibers/__init__.py
cardiac_geometries/fibers/cylinder.py
cardiac_geometries/fibers/cylinder_flat.py
cardiac_geometries/fibers/lv_ellipsoid.py
cardiac_geometries/fibers/slab.py
cardiac_geometries/fibers/utils.py
cardiac_geometriesx-0.10.5.dist-info/licenses/LICENSE
cardiac_geometriesx-0.10.5.dist-info/METADATA
cardiac_geometriesx-0.10.5.dist-info/WHEEL
cardiac_geometriesx-0.10.5.dist-info/entry_points.txt
cardiac_geometriesx-0.10.5.dist-info/top_level.txt
cardiac_geometriesx-0.10.5.dist-info/RECORD
