Metadata-Version: 2.4
Name: cardiac-geometriesx
Version: 0.10.5
Summary: A python library for cardiac geometries
Author-email: Henrik Finsberg <henriknf@simula.no>
License: MIT
Project-URL: Homepage, https://github.com/finsberg/cardiac-geometriesx
Keywords: cardiac,geometry
Classifier: License :: OSI Approved :: MIT License
Classifier: Programming Language :: Python :: 3
Classifier: Programming Language :: Python :: 3 :: Only
Requires-Python: >=3.10
License-File: LICENSE
Requires-Dist: fenics-dolfinx>=0.9.0
Requires-Dist: structlog
Requires-Dist: cardiac-geometries-core>=0.4
Requires-Dist: rich-click
Requires-Dist: adios4dolfinx
Requires-Dist: scifem
Provides-Extra: dev
Requires-Dist: bump-my-version; extra == "dev"
Requires-Dist: ipython; extra == "dev"
Requires-Dist: pdbpp; extra == "dev"
Requires-Dist: pre-commit; extra == "dev"
Requires-Dist: twine; extra == "dev"
Requires-Dist: wheel; extra == "dev"
Provides-Extra: docs
Requires-Dist: jupyter-book<2.0; extra == "docs"
Requires-Dist: jupytext; extra == "docs"
Requires-Dist: jupyter; extra == "docs"
Requires-Dist: pyvista[all]>=0.45.0; extra == "docs"
Requires-Dist: vtk>=9.5.0; extra == "docs"
Requires-Dist: trame-vuetify; extra == "docs"
Requires-Dist: ipywidgets; extra == "docs"
Requires-Dist: fenicsx-ldrb; extra == "docs"
Requires-Dist: ukb-atlas; extra == "docs"
Requires-Dist: sphinx-codeautolink; extra == "docs"
Requires-Dist: sphinx-copybutton; extra == "docs"
Provides-Extra: test
Requires-Dist: pre-commit; extra == "test"
Requires-Dist: pytest; extra == "test"
Requires-Dist: pytest-cov; extra == "test"
Requires-Dist: ukb-atlas[pyvista]; extra == "test"
Requires-Dist: fenicsx-ldrb; extra == "test"
Provides-Extra: gui
Requires-Dist: streamlit; extra == "gui"
Requires-Dist: stpyvista; extra == "gui"
Requires-Dist: pyvista[all]>=0.43.0; extra == "gui"
Requires-Dist: trame-vuetify; extra == "gui"
Requires-Dist: ipywidgets; extra == "gui"
Requires-Dist: fenicsx-ldrb; extra == "gui"
Dynamic: license-file
